inclusivity_ussd-1.0.dist-info/DESCRIPTION.rst
inclusivity_ussd-1.0.dist-info/METADATA
inclusivity_ussd-1.0.dist-info/RECORD
inclusivity_ussd-1.0.dist-info/WHEEL
inclusivity_ussd-1.0.dist-info/metadata.json
inclusivity_ussd-1.0.dist-info/top_level.txt
ussd/__init__.py
ussd/admin.py
ussd/apis.py
ussd/apps.py
ussd/built_in_functions.py
ussd/core.py
ussd/defaults.py
ussd/models.py
ussd/tasks.py
ussd/urls.py
ussd/utilities.py
ussd/views.py
ussd/filters/__init__.py
ussd/filters/date_filters.py
ussd/filters/dict_filters.py
ussd/filters/list_filters.py
ussd/filters/utility_filters.py
ussd/management/__init__.py
ussd/management/commands/__init__.py
ussd/management/commands/create_ussd_app.py
ussd/management/commands/validate_ussd_journey.py
ussd/migrations/0001_initial.py
ussd/migrations/__init__.py
ussd/screens/__init__.py
ussd/screens/custom_screen.py
ussd/screens/function_screen.py
ussd/screens/http_screen.py
ussd/screens/initial_screen.py
ussd/screens/input_screen.py
ussd/screens/menu_screen.py
ussd/screens/quit_screen.py
ussd/screens/router_screen.py
ussd/screens/serializers.py
ussd/screens/update_session_screen.py
ussd/tests/__init__.py
ussd/tests/test_built_in_functions.py
ussd/tests/test_commands.py
ussd/tests/test_core_functionaliyt.py
ussd/tests/test_custom_screen.py
ussd/tests/test_date_filters.py
ussd/tests/test_function_screen.py
ussd/tests/test_http_screen.py
ussd/tests/test_initial_screen.py
ussd/tests/test_input_screen.py
ussd/tests/test_list_screen.py
ussd/tests/test_menu_screen.py
ussd/tests/test_multi_language_support_from_session_data.py
ussd/tests/test_quit_screen.py
ussd/tests/test_report_session.py
ussd/tests/test_router_screen.py
ussd/tests/test_update_session_screen.py
ussd/tests/test_ussd_app_creation.py
ussd/tests/test_ussd_interaction.py
ussd/tests/test_utility_filters.py
ussd/tests/test_variables.py
ussd/tests/utils.py
ussd/tests/sample_screen_definition/__init__.py
ussd/tests/sample_screen_definition/invalid_custom_screen_conf.yml
ussd/tests/sample_screen_definition/invalid_function_screen_conf.yml
ussd/tests/sample_screen_definition/invalid_http_screen_conf.yml
ussd/tests/sample_screen_definition/invalid_initial_screen_conf.yml
